btm_resource_manager/__init__.py
btm_resource_manager/ci_temp_sensor.py
btm_resource_manager/resource_manager.py
ci_temp.py
ocderase.py
ocdflash.py
ocdopen.py
ocdreset.py
resource_manager_cli.py
btm_resource_manager-1.3.3.dist-info/METADATA
btm_resource_manager-1.3.3.dist-info/WHEEL
btm_resource_manager-1.3.3.dist-info/entry_points.txt
btm_resource_manager-1.3.3.dist-info/RECORD
