Metadata-Version: 2.3
Name: btm_resource_manager
Version: 1.3.3
Summary: Resource manager for CLI tools
Project-URL: Homepage, https://github.com/Analog-Devices-MSDK/btm-resource-manager
Project-URL: Repository, https://github.com/Analog-Devices-MSDK/btm-resource-manager
Project-URL: Bug Tracker, https://github.com/Analog-Devices-MSDK/btm-resource-manager/issues
Classifier: License :: OSI Approved :: MIT License
Classifier: Operating System :: OS Independent
Classifier: Programming Language :: Python :: 3
Requires-Python: >=3.8
Requires-Dist: rich
Requires-Dist: tabulate>=0.9.0
